<?xml version="1.0" ?>
<container xmlns="http://symfony.com/schema/dic/services"
           xmlns:xsi="http://www.w3.org/2001/XMLSchema-instance"
           xsi:schemaLocation="http://symfony.com/schema/dic/services http://symfony.com/schema/dic/services/services-1.0.xsd">
<parameters>
        <parameter key="lunetics_locale.request_listener.class">Lunetics\LocaleBundle\EventListener\RequestListener</parameter>
    </parameters>
    <services>
        
        <service id="lunetics_locale.router_guesser" class="%lunetics_locale.router_guesser.class%">
            <argument>%lunetics_locale.router_guesser.check_query%</argument>
        </service>
        
        <service id="lunetics_locale.browser_guesser" class="%lunetics_locale.browser_guesser.class%">
            <argument>%locale%</argument>
            <argument>%lunetics_locale.allowed_locales%</argument>
        </service>
        
        <service id="lunetics_locale.cookie_guesser" class="%lunetics_locale.cookie_guesser.class%">
            <argument>%lunetics_locale.cookie.name%</argument>
        </service>
        
        <service id="lunetics_locale.guesser_manager" class="%lunetics_locale.guesser_manager.class%">
            <argument>%lunetics_locale.guessing_order%</argument>
            <argument type="service" id="lunetics_locale.router_guesser" />
            <argument type="service" id="lunetics_locale.browser_guesser" />
            <argument type="service" id="lunetics_locale.cookie_guesser" />
        </service>
        
        <service id="lunetics_locale.locale_cookie" class="%lunetics_locale.cookie.class%">
            <argument>%lunetics_locale.cookie.name%</argument>
            <argument>%lunetics_locale.cookie.ttl%</argument>
            <argument>%lunetics_locale.cookie.path%</argument>
            <argument>%lunetics_locale.cookie.domain%</argument>
            <argument>%lunetics_locale.cookie.secure%</argument>
            <argument>%lunetics_locale.cookie.httpOnly%</argument>
        </service>
        
        <service id="lunetics_locale.locale_listener" class="%lunetics_locale.request_listener.class%">
            <argument>%locale%</argument>
            <argument type="service" id="lunetics_locale.guesser_manager" />
            <argument type="service" id="logger" />
            <call method="setEventDispatcher">
                <argument type="service" id="event_dispatcher"/>
            </call>
            <tag name="kernel.event_listener" event="kernel.request" method="onRequest"/>
        </service>
    </services>
</container>