<?xml version="1.0" ?>
<container xmlns="http://symfony.com/schema/dic/services"
           xmlns:xsi="http://www.w3.org/2001/XMLSchema-instance"
           xsi:schemaLocation="http://symfony.com/schema/dic/services http://symfony.com/schema/dic/services/services-1.0.xsd">
    <services>

        <service id="lunetics_locale.switcher_helper"
                 class="Lunetics\LocaleBundle\Templating\Helper\LocaleSwitchHelper">
            <argument type="service" id="templating"/>
            <argument>%lunetics_locale.switcher.template%</argument>
            <tag name="templating.helper" alias="switch"/>
        </service>

        <service id="lunetics_locale.twig.change_language"
                 class="Lunetics\LocaleBundle\Twig\Extension\ChangeLanguageExtension">
            <call method="setServiceContainer">
                <argument type="service" id="service_container"/>
            </call>
            <tag name="twig.extension"/>
        </service>

        <service id="lunetics_locale.twig.switcher"
                 class="Lunetics\LocaleBundle\Twig\Extension\LocaleSwitcherExtension">
            <argument type="service" id="service_container"/>
            <tag name="twig.extension"/>
        </service>

        <service id="lunetics_locale.switcher_controller" class="Lunetics\LocaleBundle\Controller\LocaleController" scope="request">
            <argument type="service" id="router"/>
            <argument type="service" id="lunetics_locale.validator.meta" />
            <argument>%lunetics_locale.switcher.use_referrer%</argument>
            <argument>%lunetics_locale.switcher.redirect_to_route%</argument>
            <argument>%lunetics_locale.switcher.redirect_statuscode%</argument>
        </service>

    </services>
</container>
